{
    "Game Objects": {
        "Count": 43,
        "GameObject 1": {
            "Components": {
                "Transform": {
                    "Active": true,
                    "Parent UUID": 1644443353,
                    "Rotation": [
                        0.0,
                        0.0,
                        0.0,
                        1.0
                    ],
                    "Scale": [
                        1.0,
                        1.0,
                        1.0
                    ],
                    "Translation": [
                        0.0,
                        0.0,
                        0.0
                    ],
                    "UUID": 1142490349
                }
            },
            "Name": "street environment_v01",
            "Parent UUID": 0,
            "UUID": 1644443353
        },
        "GameObject 10": {
            "Components": {
                "Transform": {
                    "Active": true,
                    "Parent UUID": 851343266,
                    "Rotation": [
                        0.0,
                        0.0,
                        0.7071067690849304,
                        0.7071067690849304
                    ],
                    "Scale": [
                        1.0,
                        1.0,
                        1.0
                    ],
                    "Translation": [
                        25.154010772705078,
                        -39.15372085571289,
                        8.553864176974457e-07
                    ],
                    "UUID": 820864986
                }
            },
            "Name": "City_building_010",
            "Parent UUID": 346731287,
            "UUID": 851343266
        },
        "GameObject 11": {
            "Components": {
                "Material": {
                    "Active": true,
                    "Parent UUID": 606376342,
                    "Resource UUID": 1271731231,
                    "UUID": 1909098255
                },
                "Mesh": {
                    "Active": true,
                    "F_Normals on": false,
                    "Parent UUID": 606376342,
                    "Resource UUID": 1202786986,
                    "UUID": 596751288,
                    "V_Normals on": false
                },
                "Transform": {
                    "Active": true,
                    "Parent UUID": 606376342,
                    "Rotation": [
                        0.0,
                        0.0,
                        0.0,
                        1.0
                    ],
                    "Scale": [
                        1.0,
                        1.0,
                        1.0
                    ],
                    "Translation": [
                        0.0,
                        0.0,
                        0.0
                    ],
                    "UUID": 1293773656
                }
            },
            "Name": "City_building_010_Parent",
            "Parent UUID": 851343266,
            "UUID": 606376342
        },
        "GameObject 12": {
            "Components": {
                "Material": {
                    "Active": true,
                    "Parent UUID": 255421188,
                    "Resource UUID": 1858233146,
                    "UUID": 855830741
                },
                "Mesh": {
                    "Active": true,
                    "F_Normals on": false,
                    "Parent UUID": 255421188,
                    "Resource UUID": 2121519325,
                    "UUID": 1192511445,
                    "V_Normals on": false
                },
                "Transform": {
                    "Active": true,
                    "Parent UUID": 255421188,
                    "Rotation": [
                        0.0,
                        0.0,
                        0.0,
                        1.0
                    ],
                    "Scale": [
                        1.0,
                        1.0,
                        1.0
                    ],
                    "Translation": [
                        0.0,
                        0.0,
                        0.0
                    ],
                    "UUID": 1513932588
                }
            },
            "Name": "City_building_010_SubMesh",
            "Parent UUID": 851343266,
            "UUID": 255421188
        },
        "GameObject 13": {
            "Components": {
                "Material": {
                    "Active": true,
                    "Parent UUID": 519168812,
                    "Resource UUID": 1703764197,
                    "UUID": 1946704934
                },
                "Mesh": {
                    "Active": true,
                    "F_Normals on": false,
                    "Parent UUID": 519168812,
                    "Resource UUID": 824219090,
                    "UUID": 1507917292,
                    "V_Normals on": false
                },
                "Transform": {
                    "Active": true,
                    "Parent UUID": 519168812,
                    "Rotation": [
                        0.0,
                        0.0,
                        0.0,
                        1.0
                    ],
                    "Scale": [
                        1.0,
                        1.0,
                        1.0
                    ],
                    "Translation": [
                        30.134540557861328,
                        37.4932861328125,
                        -1.5106878663573298e-06
                    ],
                    "UUID": 754597595
                }
            },
            "Name": "City_building_011",
            "Parent UUID": 346731287,
            "UUID": 519168812
        },
        "GameObject 14": {
            "Components": {
                "Material": {
                    "Active": true,
                    "Parent UUID": 46733403,
                    "Resource UUID": 622495105,
                    "UUID": 2030496201
                },
                "Mesh": {
                    "Active": true,
                    "F_Normals on": false,
                    "Parent UUID": 46733403,
                    "Resource UUID": 228644082,
                    "UUID": 364225098,
                    "V_Normals on": false
                },
                "Transform": {
                    "Active": true,
                    "Parent UUID": 46733403,
                    "Rotation": [
                        0.0,
                        0.0,
                        0.7071067690849304,
                        0.7071067690849304
                    ],
                    "Scale": [
                        1.0,
                        1.0,
                        1.0
                    ],
                    "Translation": [
                        -42.288055419921875,
                        33.201576232910156,
                        5.014607040720875e-07
                    ],
                    "UUID": 188525058
                }
            },
            "Name": "City_building_013",
            "Parent UUID": 346731287,
            "UUID": 46733403
        },
        "GameObject 15": {
            "Components": {
                "Material": {
                    "Active": true,
                    "Parent UUID": 1280841358,
                    "Resource UUID": 416937446,
                    "UUID": 12344126
                },
                "Mesh": {
                    "Active": true,
                    "F_Normals on": false,
                    "Parent UUID": 1280841358,
                    "Resource UUID": 1228705073,
                    "UUID": 65471467,
                    "V_Normals on": false
                },
                "Transform": {
                    "Active": true,
                    "Parent UUID": 1280841358,
                    "Rotation": [
                        0.0,
                        0.0,
                        1.0,
                        -4.371138828673793e-08
                    ],
                    "Scale": [
                        1.0,
                        1.0,
                        1.0
                    ],
                    "Translation": [
                        -19.439706802368164,
                        32.061729431152344,
                        0.0
                    ],
                    "UUID": 1345227290
                }
            },
            "Name": "City_building_014",
            "Parent UUID": 346731287,
            "UUID": 1280841358
        },
        "GameObject 16": {
            "Components": {
                "Transform": {
                    "Active": true,
                    "Parent UUID": 812292735,
                    "Rotation": [
                        0.0,
                        0.0,
                        1.0,
                        -4.371138828673793e-08
                    ],
                    "Scale": [
                        1.0,
                        1.0,
                        1.0
                    ],
                    "Translation": [
                        34.270423889160156,
                        -41.972747802734375,
                        8.553864176974457e-07
                    ],
                    "UUID": 798143337
                }
            },
            "Name": "City_building_016",
            "Parent UUID": 346731287,
            "UUID": 812292735
        },
        "GameObject 17": {
            "Components": {
                "Material": {
                    "Active": true,
                    "Parent UUID": 1397899152,
                    "Resource UUID": 1313099917,
                    "UUID": 539658142
                },
                "Mesh": {
                    "Active": true,
                    "F_Normals on": false,
                    "Parent UUID": 1397899152,
                    "Resource UUID": 17966549,
                    "UUID": 950468667,
                    "V_Normals on": false
                },
                "Transform": {
                    "Active": true,
                    "Parent UUID": 1397899152,
                    "Rotation": [
                        0.0,
                        0.0,
                        0.0,
                        1.0
                    ],
                    "Scale": [
                        1.0,
                        1.0,
                        1.0
                    ],
                    "Translation": [
                        0.0,
                        0.0,
                        0.0
                    ],
                    "UUID": 1325462999
                }
            },
            "Name": "City_building_016_Parent",
            "Parent UUID": 812292735,
            "UUID": 1397899152
        },
        "GameObject 18": {
            "Components": {
                "Material": {
                    "Active": true,
                    "Parent UUID": 1013625375,
                    "Resource UUID": 488003215,
                    "UUID": 305622671
                },
                "Mesh": {
                    "Active": true,
                    "F_Normals on": false,
                    "Parent UUID": 1013625375,
                    "Resource UUID": 1223125325,
                    "UUID": 2080535975,
                    "V_Normals on": false
                },
                "Transform": {
                    "Active": true,
                    "Parent UUID": 1013625375,
                    "Rotation": [
                        0.0,
                        0.0,
                        0.0,
                        1.0
                    ],
                    "Scale": [
                        1.0,
                        1.0,
                        1.0
                    ],
                    "Translation": [
                        0.0,
                        0.0,
                        0.0
                    ],
                    "UUID": 1152108808
                }
            },
            "Name": "City_building_016_SubMesh",
            "Parent UUID": 812292735,
            "UUID": 1013625375
        },
        "GameObject 19": {
            "Components": {
                "Transform": {
                    "Active": true,
                    "Parent UUID": 1039197334,
                    "Rotation": [
                        0.0,
                        0.0,
                        0.7071067690849304,
                        0.7071067690849304
                    ],
                    "Scale": [
                        1.0,
                        1.0,
                        1.0
                    ],
                    "Translation": [
                        44.26008224487305,
                        -39.15372085571289,
                        8.553864176974457e-07
                    ],
                    "UUID": 1233522984
                }
            },
            "Name": "City_building_017",
            "Parent UUID": 346731287,
            "UUID": 1039197334
        },
        "GameObject 2": {
            "Components": {
                "Transform": {
                    "Active": true,
                    "Parent UUID": 673786496,
                    "Rotation": [
                        -0.9999999403953552,
                        0.0,
                        0.0,
                        0.0
                    ],
                    "Scale": [
                        1.0,
                        1.0,
                        1.0
                    ],
                    "Translation": [
                        18.153732299804688,
                        0.0,
                        58.96091079711914
                    ],
                    "UUID": 56852948
                }
            },
            "Name": "Sky001",
            "Parent UUID": 1644443353,
            "UUID": 673786496
        },
        "GameObject 20": {
            "Components": {
                "Material": {
                    "Active": true,
                    "Parent UUID": 1232625534,
                    "Resource UUID": 1713654569,
                    "UUID": 1704476595
                },
                "Mesh": {
                    "Active": true,
                    "F_Normals on": false,
                    "Parent UUID": 1232625534,
                    "Resource UUID": 433353045,
                    "UUID": 743255617,
                    "V_Normals on": false
                },
                "Transform": {
                    "Active": true,
                    "Parent UUID": 1232625534,
                    "Rotation": [
                        0.0,
                        0.0,
                        0.0,
                        1.0
                    ],
                    "Scale": [
                        1.0,
                        1.0,
                        1.0
                    ],
                    "Translation": [
                        0.0,
                        0.0,
                        0.0
                    ],
                    "UUID": 1028284847
                }
            },
            "Name": "City_building_017_Parent",
            "Parent UUID": 1039197334,
            "UUID": 1232625534
        },
        "GameObject 21": {
            "Components": {
                "Material": {
                    "Active": true,
                    "Parent UUID": 474589242,
                    "Resource UUID": 1296701555,
                    "UUID": 1549657828
                },
                "Mesh": {
                    "Active": true,
                    "F_Normals on": false,
                    "Parent UUID": 474589242,
                    "Resource UUID": 234396817,
                    "UUID": 1741408069,
                    "V_Normals on": false
                },
                "Transform": {
                    "Active": true,
                    "Parent UUID": 474589242,
                    "Rotation": [
                        0.0,
                        0.0,
                        0.0,
                        1.0
                    ],
                    "Scale": [
                        1.0,
                        1.0,
                        1.0
                    ],
                    "Translation": [
                        0.0,
                        0.0,
                        0.0
                    ],
                    "UUID": 194224540
                }
            },
            "Name": "City_building_017_SubMesh",
            "Parent UUID": 1039197334,
            "UUID": 474589242
        },
        "GameObject 22": {
            "Components": {
                "Material": {
                    "Active": true,
                    "Parent UUID": 212562804,
                    "Resource UUID": 1240013718,
                    "UUID": 1659558972
                },
                "Mesh": {
                    "Active": true,
                    "F_Normals on": false,
                    "Parent UUID": 212562804,
                    "Resource UUID": 120494884,
                    "UUID": 4967831,
                    "V_Normals on": false
                },
                "Transform": {
                    "Active": true,
                    "Parent UUID": 212562804,
                    "Rotation": [
                        0.0,
                        0.0,
                        1.0,
                        1.9470718370939721e-07
                    ],
                    "Scale": [
                        1.0,
                        1.0,
                        1.0
                    ],
                    "Translation": [
                        -20.831323623657227,
                        -27.426488876342773,
                        0.0
                    ],
                    "UUID": 525165807
                }
            },
            "Name": "City_building_022",
            "Parent UUID": 346731287,
            "UUID": 212562804
        },
        "GameObject 23": {
            "Components": {
                "Material": {
                    "Active": true,
                    "Parent UUID": 903193782,
                    "Resource UUID": 1954019543,
                    "UUID": 2002723672
                },
                "Mesh": {
                    "Active": true,
                    "F_Normals on": false,
                    "Parent UUID": 903193782,
                    "Resource UUID": 1911855355,
                    "UUID": 2000533047,
                    "V_Normals on": false
                },
                "Transform": {
                    "Active": true,
                    "Parent UUID": 903193782,
                    "Rotation": [
                        0.0,
                        0.0,
                        0.0,
                        1.0
                    ],
                    "Scale": [
                        1.0,
                        1.0,
                        1.0
                    ],
                    "Translation": [
                        42.13064193725586,
                        37.4932861328125,
                        -1.5106878663573298e-06
                    ],
                    "UUID": 785628815
                }
            },
            "Name": "City_building_023",
            "Parent UUID": 346731287,
            "UUID": 903193782
        },
        "GameObject 24": {
            "Components": {
                "Material": {
                    "Active": true,
                    "Parent UUID": 2097745748,
                    "Resource UUID": 1460042857,
                    "UUID": 1093951072
                },
                "Mesh": {
                    "Active": true,
                    "F_Normals on": false,
                    "Parent UUID": 2097745748,
                    "Resource UUID": 1399271018,
                    "UUID": 652800099,
                    "V_Normals on": false
                },
                "Transform": {
                    "Active": true,
                    "Parent UUID": 2097745748,
                    "Rotation": [
                        0.0,
                        0.0,
                        1.0,
                        4.371138828673793e-08
                    ],
                    "Scale": [
                        1.0,
                        1.0,
                        1.0
                    ],
                    "Translation": [
                        -20.572771072387695,
                        43.060829162597656,
                        -0.06919445842504501
                    ],
                    "UUID": 1088856332
                }
            },
            "Name": "City_building_024",
            "Parent UUID": 346731287,
            "UUID": 2097745748
        },
        "GameObject 25": {
            "Components": {
                "Material": {
                    "Active": true,
                    "Parent UUID": 199381670,
                    "Resource UUID": 1308105039,
                    "UUID": 1390650247
                },
                "Mesh": {
                    "Active": true,
                    "F_Normals on": false,
                    "Parent UUID": 199381670,
                    "Resource UUID": 1772700343,
                    "UUID": 1094418243,
                    "V_Normals on": false
                },
                "Transform": {
                    "Active": true,
                    "Parent UUID": 199381670,
                    "Rotation": [
                        0.0,
                        0.0,
                        1.0,
                        4.371138828673793e-08
                    ],
                    "Scale": [
                        1.0,
                        1.0,
                        1.0
                    ],
                    "Translation": [
                        31.51188850402832,
                        -16.446016311645508,
                        0.0
                    ],
                    "UUID": 1964436509
                }
            },
            "Name": "City_building_026",
            "Parent UUID": 346731287,
            "UUID": 199381670
        },
        "GameObject 26": {
            "Components": {
                "Material": {
                    "Active": true,
                    "Parent UUID": 1285386913,
                    "Resource UUID": 1416519557,
                    "UUID": 1290095985
                },
                "Mesh": {
                    "Active": true,
                    "F_Normals on": false,
                    "Parent UUID": 1285386913,
                    "Resource UUID": 1391988400,
                    "UUID": 616556716,
                    "V_Normals on": false
                },
                "Transform": {
                    "Active": true,
                    "Parent UUID": 1285386913,
                    "Rotation": [
                        0.0,
                        0.0,
                        0.0,
                        1.0
                    ],
                    "Scale": [
                        1.0,
                        1.0,
                        1.0
                    ],
                    "Translation": [
                        13.38798999786377,
                        -33.75503921508789,
                        -9.383451811117993e-07
                    ],
                    "UUID": 2131215836
                }
            },
            "Name": "City_building_028",
            "Parent UUID": 346731287,
            "UUID": 1285386913
        },
        "GameObject 27": {
            "Components": {
                "Material": {
                    "Active": true,
                    "Parent UUID": 2129858231,
                    "Resource UUID": 487801424,
                    "UUID": 1047915855
                },
                "Mesh": {
                    "Active": true,
                    "F_Normals on": false,
                    "Parent UUID": 2129858231,
                    "Resource UUID": 564954208,
                    "UUID": 916546646,
                    "V_Normals on": false
                },
                "Transform": {
                    "Active": true,
                    "Parent UUID": 2129858231,
                    "Rotation": [
                        0.0,
                        0.0,
                        0.0,
                        1.0
                    ],
                    "Scale": [
                        1.0,
                        1.0,
                        1.0
                    ],
                    "Translation": [
                        -2.5033531188964844,
                        15.800846099853516,
                        0.0
                    ],
                    "UUID": 1261558748
                }
            },
            "Name": "Object010",
            "Parent UUID": 346731287,
            "UUID": 2129858231
        },
        "GameObject 28": {
            "Components": {
                "Material": {
                    "Active": true,
                    "Parent UUID": 1513920363,
                    "Resource UUID": 1685448609,
                    "UUID": 1776993592
                },
                "Mesh": {
                    "Active": true,
                    "F_Normals on": false,
                    "Parent UUID": 1513920363,
                    "Resource UUID": 421984235,
                    "UUID": 1963651462,
                    "V_Normals on": false
                },
                "Transform": {
                    "Active": true,
                    "Parent UUID": 1513920363,
                    "Rotation": [
                        0.0,
                        0.0,
                        -0.7071067690849304,
                        0.7071067690849304
                    ],
                    "Scale": [
                        1.0,
                        1.0,
                        1.0
                    ],
                    "Translation": [
                        -42.8072395324707,
                        -41.83556365966797,
                        -9.383451811117993e-07
                    ],
                    "UUID": 4714016
                }
            },
            "Name": "City_building_030",
            "Parent UUID": 346731287,
            "UUID": 1513920363
        },
        "GameObject 29": {
            "Components": {
                "Material": {
                    "Active": true,
                    "Parent UUID": 1388133975,
                    "Resource UUID": 1043783714,
                    "UUID": 2080440863
                },
                "Mesh": {
                    "Active": true,
                    "F_Normals on": false,
                    "Parent UUID": 1388133975,
                    "Resource UUID": 524401109,
                    "UUID": 566821561,
                    "V_Normals on": false
                },
                "Transform": {
                    "Active": true,
                    "Parent UUID": 1388133975,
                    "Rotation": [
                        0.0,
                        0.0,
                        -0.7071067690849304,
                        0.7071067690849304
                    ],
                    "Scale": [
                        1.0,
                        1.0,
                        1.0
                    ],
                    "Translation": [
                        -34.679481506347656,
                        -41.83556365966797,
                        -9.383451811117993e-07
                    ],
                    "UUID": 68907534
                }
            },
            "Name": "City_building_031",
            "Parent UUID": 346731287,
            "UUID": 1388133975
        },
        "GameObject 3": {
            "Components": {
                "Transform": {
                    "Active": true,
                    "Parent UUID": 346731287,
                    "Rotation": [
                        -0.7071067690849304,
                        0.0,
                        0.0,
                        0.7071067690849304
                    ],
                    "Scale": [
                        1.0,
                        1.0,
                        1.0
                    ],
                    "Translation": [
                        0.0,
                        0.0,
                        0.0
                    ],
                    "UUID": 2062739947
                }
            },
            "Name": "Dummy001",
            "Parent UUID": 1644443353,
            "UUID": 346731287
        },
        "GameObject 30": {
            "Components": {
                "Material": {
                    "Active": true,
                    "Parent UUID": 2107610689,
                    "Resource UUID": 1899400488,
                    "UUID": 80348556
                },
                "Mesh": {
                    "Active": true,
                    "F_Normals on": false,
                    "Parent UUID": 2107610689,
                    "Resource UUID": 113915475,
                    "UUID": 413360082,
                    "V_Normals on": false
                },
                "Transform": {
                    "Active": true,
                    "Parent UUID": 2107610689,
                    "Rotation": [
                        0.0,
                        0.0,
                        0.0,
                        1.0
                    ],
                    "Scale": [
                        1.0,
                        1.0,
                        1.0
                    ],
                    "Translation": [
                        -29.478403091430664,
                        21.01409912109375,
                        0.0
                    ],
                    "UUID": 701146653
                }
            },
            "Name": "City_building_032",
            "Parent UUID": 346731287,
            "UUID": 2107610689
        },
        "GameObject 31": {
            "Components": {
                "Material": {
                    "Active": true,
                    "Parent UUID": 252176604,
                    "Resource UUID": 445813186,
                    "UUID": 898870553
                },
                "Mesh": {
                    "Active": true,
                    "F_Normals on": false,
                    "Parent UUID": 252176604,
                    "Resource UUID": 1042954143,
                    "UUID": 378672415,
                    "V_Normals on": false
                },
                "Transform": {
                    "Active": true,
                    "Parent UUID": 252176604,
                    "Rotation": [
                        0.0,
                        0.0,
                        0.0,
                        1.0
                    ],
                    "Scale": [
                        1.0,
                        1.0,
                        1.0
                    ],
                    "Translation": [
                        -32.36149597167969,
                        42.37042236328125,
                        5.014607040720875e-07
                    ],
                    "UUID": 1108532859
                }
            },
            "Name": "City_building_033",
            "Parent UUID": 346731287,
            "UUID": 252176604
        },
        "GameObject 32": {
            "Components": {
                "Material": {
                    "Active": true,
                    "Parent UUID": 793317439,
                    "Resource UUID": 898730363,
                    "UUID": 125985291
                },
                "Mesh": {
                    "Active": true,
                    "F_Normals on": false,
                    "Parent UUID": 793317439,
                    "Resource UUID": 941075306,
                    "UUID": 1423063431,
                    "V_Normals on": false
                },
                "Transform": {
                    "Active": true,
                    "Parent UUID": 793317439,
                    "Rotation": [
                        0.0,
                        0.0,
                        -0.7071068286895752,
                        0.7071067094802856
                    ],
                    "Scale": [
                        1.0,
                        1.0,
                        1.0
                    ],
                    "Translation": [
                        16.049516677856445,
                        -16.696884155273438,
                        0.0
                    ],
                    "UUID": 421503426
                }
            },
            "Name": "City_building_034",
            "Parent UUID": 346731287,
            "UUID": 793317439
        },
        "GameObject 33": {
            "Components": {
                "Material": {
                    "Active": true,
                    "Parent UUID": 1025292703,
                    "Resource UUID": 210817278,
                    "UUID": 2023673467
                },
                "Mesh": {
                    "Active": true,
                    "F_Normals on": false,
                    "Parent UUID": 1025292703,
                    "Resource UUID": 899560581,
                    "UUID": 1406468040,
                    "V_Normals on": false
                },
                "Transform": {
                    "Active": true,
                    "Parent UUID": 1025292703,
                    "Rotation": [
                        0.0,
                        0.0,
                        0.0,
                        1.0
                    ],
                    "Scale": [
                        1.0,
                        1.0,
                        1.0
                    ],
                    "Translation": [
                        13.38798999786377,
                        -40.80251693725586,
                        -9.383451811117993e-07
                    ],
                    "UUID": 1694332930
                }
            },
            "Name": "City_building_035",
            "Parent UUID": 346731287,
            "UUID": 1025292703
        },
        "GameObject 34": {
            "Components": {
                "Material": {
                    "Active": true,
                    "Parent UUID": 1241612340,
                    "Resource UUID": 756251692,
                    "UUID": 1090517130
                },
                "Mesh": {
                    "Active": true,
                    "F_Normals on": false,
                    "Parent UUID": 1241612340,
                    "Resource UUID": 1768879107,
                    "UUID": 1142475233,
                    "V_Normals on": false
                },
                "Transform": {
                    "Active": true,
                    "Parent UUID": 1241612340,
                    "Rotation": [
                        0.0,
                        0.0,
                        -0.7071067690849304,
                        0.7071067690849304
                    ],
                    "Scale": [
                        1.0,
                        1.0,
                        1.0
                    ],
                    "Translation": [
                        -31.216331481933594,
                        33.201576232910156,
                        5.014607040720875e-07
                    ],
                    "UUID": 1780964096
                }
            },
            "Name": "City_building_036",
            "Parent UUID": 346731287,
            "UUID": 1241612340
        },
        "GameObject 35": {
            "Components": {
                "Material": {
                    "Active": true,
                    "Parent UUID": 1535087585,
                    "Resource UUID": 236705223,
                    "UUID": 1848040454
                },
                "Mesh": {
                    "Active": true,
                    "F_Normals on": false,
                    "Parent UUID": 1535087585,
                    "Resource UUID": 1291104306,
                    "UUID": 2012307052,
                    "V_Normals on": false
                },
                "Transform": {
                    "Active": true,
                    "Parent UUID": 1535087585,
                    "Rotation": [
                        0.0,
                        0.0,
                        1.0,
                        1.9470718370939721e-07
                    ],
                    "Scale": [
                        1.0,
                        1.0,
                        1.0
                    ],
                    "Translation": [
                        -20.31769371032715,
                        -16.16360855102539,
                        0.0
                    ],
                    "UUID": 514095036
                }
            },
            "Name": "City_building_037",
            "Parent UUID": 346731287,
            "UUID": 1535087585
        },
        "GameObject 36": {
            "Components": {
                "Material": {
                    "Active": true,
                    "Parent UUID": 749875547,
                    "Resource UUID": 894181845,
                    "UUID": 2121031186
                },
                "Mesh": {
                    "Active": true,
                    "F_Normals on": false,
                    "Parent UUID": 749875547,
                    "Resource UUID": 125126300,
                    "UUID": 430787862,
                    "V_Normals on": false
                },
                "Transform": {
                    "Active": true,
                    "Parent UUID": 749875547,
                    "Rotation": [
                        0.0,
                        0.0,
                        -0.7071068286895752,
                        0.7071067094802856
                    ],
                    "Scale": [
                        1.0,
                        1.0,
                        1.0
                    ],
                    "Translation": [
                        -41.64900207519531,
                        -16.495393753051758,
                        0.0
                    ],
                    "UUID": 1757999117
                }
            },
            "Name": "City_building_038",
            "Parent UUID": 346731287,
            "UUID": 749875547
        },
        "GameObject 37": {
            "Components": {
                "Material": {
                    "Active": true,
                    "Parent UUID": 1224460068,
                    "Resource UUID": 1059026299,
                    "UUID": 2027078638
                },
                "Mesh": {
                    "Active": true,
                    "F_Normals on": false,
                    "Parent UUID": 1224460068,
                    "Resource UUID": 1698490272,
                    "UUID": 913910228,
                    "V_Normals on": false
                },
                "Transform": {
                    "Active": true,
                    "Parent UUID": 1224460068,
                    "Rotation": [
                        0.0,
                        0.0,
                        -0.7071067690849304,
                        0.7071067690849304
                    ],
                    "Scale": [
                        1.0,
                        1.0,
                        1.0
                    ],
                    "Translation": [
                        -42.8072395324707,
                        -30.643888473510742,
                        -9.383451811117993e-07
                    ],
                    "UUID": 1623542916
                }
            },
            "Name": "City_building_039",
            "Parent UUID": 346731287,
            "UUID": 1224460068
        },
        "GameObject 38": {
            "Components": {
                "Material": {
                    "Active": true,
                    "Parent UUID": 1551688504,
                    "Resource UUID": 750331867,
                    "UUID": 9140999
                },
                "Mesh": {
                    "Active": true,
                    "F_Normals on": false,
                    "Parent UUID": 1551688504,
                    "Resource UUID": 1071028186,
                    "UUID": 1315199132,
                    "V_Normals on": false
                },
                "Transform": {
                    "Active": true,
                    "Parent UUID": 1551688504,
                    "Rotation": [
                        0.0,
                        0.0,
                        -0.7071067690849304,
                        0.7071067690849304
                    ],
                    "Scale": [
                        1.0,
                        1.0,
                        1.0
                    ],
                    "Translation": [
                        -34.679481506347656,
                        -30.643888473510742,
                        -9.383451811117993e-07
                    ],
                    "UUID": 940474649
                }
            },
            "Name": "City_building_040",
            "Parent UUID": 346731287,
            "UUID": 1551688504
        },
        "GameObject 39": {
            "Components": {
                "Material": {
                    "Active": true,
                    "Parent UUID": 1126146372,
                    "Resource UUID": 1023237889,
                    "UUID": 1004462457
                },
                "Mesh": {
                    "Active": true,
                    "F_Normals on": false,
                    "Parent UUID": 1126146372,
                    "Resource UUID": 1907586286,
                    "UUID": 370048138,
                    "V_Normals on": false
                },
                "Transform": {
                    "Active": true,
                    "Parent UUID": 1126146372,
                    "Rotation": [
                        0.0,
                        0.0,
                        0.7071067690849304,
                        0.7071067690849304
                    ],
                    "Scale": [
                        1.0,
                        1.0,
                        1.0
                    ],
                    "Translation": [
                        30.69527816772461,
                        21.612646102905273,
                        2.121072952832037e-07
                    ],
                    "UUID": 956096689
                }
            },
            "Name": "City_building_041",
            "Parent UUID": 346731287,
            "UUID": 1126146372
        },
        "GameObject 4": {
            "Components": {
                "Material": {
                    "Active": true,
                    "Parent UUID": 1343924256,
                    "Resource UUID": 876633654,
                    "UUID": 393938471
                },
                "Mesh": {
                    "Active": true,
                    "F_Normals on": false,
                    "Parent UUID": 1343924256,
                    "Resource UUID": 70128045,
                    "UUID": 626377394,
                    "V_Normals on": false
                },
                "Transform": {
                    "Active": true,
                    "Parent UUID": 1343924256,
                    "Rotation": [
                        0.0,
                        0.0,
                        0.0,
                        1.0
                    ],
                    "Scale": [
                        1.0,
                        1.0,
                        1.0
                    ],
                    "Translation": [
                        -41.47589111328125,
                        21.01409912109375,
                        0.0
                    ],
                    "UUID": 1635610833
                }
            },
            "Name": "City_building_004",
            "Parent UUID": 346731287,
            "UUID": 1343924256
        },
        "GameObject 40": {
            "Components": {
                "Transform": {
                    "Active": true,
                    "Parent UUID": 1233636185,
                    "Rotation": [
                        0.04933978617191315,
                        0.932287335395813,
                        0.13933119177818298,
                        -0.3301403522491455
                    ],
                    "Scale": [
                        1.0,
                        0.9999999403953552,
                        0.9999999403953552
                    ],
                    "Translation": [
                        -78.31243133544922,
                        45.251216888427734,
                        -97.03111267089844
                    ],
                    "UUID": 523857767
                }
            },
            "Name": "Camera001",
            "Parent UUID": 1644443353,
            "UUID": 1233636185
        },
        "GameObject 41": {
            "Components": {
                "Transform": {
                    "Active": true,
                    "Parent UUID": 786819306,
                    "Rotation": [
                        0.04933978617191315,
                        0.932287335395813,
                        0.13933119177818298,
                        -0.33014047145843506
                    ],
                    "Scale": [
                        1.0,
                        0.9999999403953552,
                        0.9999999403953552
                    ],
                    "Translation": [
                        -28.13262176513672,
                        20.873329162597656,
                        -35.064212799072266
                    ],
                    "UUID": 1134035350
                }
            },
            "Name": "Camera001.Target",
            "Parent UUID": 1644443353,
            "UUID": 786819306
        },
        "GameObject 42": {
            "Components": {
                "Transform": {
                    "Active": true,
                    "Parent UUID": 438820395,
                    "Rotation": [
                        -0.6900351047515869,
                        -0.15443938970565796,
                        -0.6900351047515869,
                        0.15443941950798035
                    ],
                    "Scale": [
                        1.0,
                        1.0,
                        1.0
                    ],
                    "Translation": [
                        -66.72126770019531,
                        141.9341278076172,
                        6.204137662280118e-06
                    ],
                    "UUID": 1012358073
                }
            },
            "Name": "Spot001",
            "Parent UUID": 1644443353,
            "UUID": 438820395
        },
        "GameObject 43": {
            "Components": {
                "Transform": {
                    "Active": true,
                    "Parent UUID": 968105793,
                    "Rotation": [
                        5.960464477539063e-08,
                        0.0,
                        0.0,
                        0.9999999403953552
                    ],
                    "Scale": [
                        1.0,
                        1.0,
                        1.0
                    ],
                    "Translation": [
                        28.890945434570313,
                        -60.96388244628906,
                        -2.6648158382158726e-06
                    ],
                    "UUID": 1719153358
                }
            },
            "Name": "Spot001.Target",
            "Parent UUID": 1644443353,
            "UUID": 968105793
        },
        "GameObject 5": {
            "Components": {
                "Material": {
                    "Active": true,
                    "Parent UUID": 1154291314,
                    "Resource UUID": 279239629,
                    "UUID": 1704024157
                },
                "Mesh": {
                    "Active": true,
                    "F_Normals on": false,
                    "Parent UUID": 1154291314,
                    "Resource UUID": 1587884574,
                    "UUID": 1920237965,
                    "V_Normals on": false
                },
                "Transform": {
                    "Active": true,
                    "Parent UUID": 1154291314,
                    "Rotation": [
                        0.0,
                        0.0,
                        0.0,
                        1.0
                    ],
                    "Scale": [
                        1.0,
                        1.0,
                        1.0
                    ],
                    "Translation": [
                        17.707164764404297,
                        20.05327606201172,
                        2.121072952832037e-07
                    ],
                    "UUID": 1930017607
                }
            },
            "Name": "City_building_001",
            "Parent UUID": 346731287,
            "UUID": 1154291314
        },
        "GameObject 6": {
            "Components": {
                "Material": {
                    "Active": true,
                    "Parent UUID": 1948746188,
                    "Resource UUID": 551058388,
                    "UUID": 1054332595
                },
                "Mesh": {
                    "Active": true,
                    "F_Normals on": false,
                    "Parent UUID": 1948746188,
                    "Resource UUID": 1442434911,
                    "UUID": 440677293,
                    "V_Normals on": false
                },
                "Transform": {
                    "Active": true,
                    "Parent UUID": 1948746188,
                    "Rotation": [
                        0.0,
                        0.0,
                        0.0,
                        1.0
                    ],
                    "Scale": [
                        1.0,
                        1.0,
                        1.0
                    ],
                    "Translation": [
                        16.0104923248291,
                        37.4932861328125,
                        -1.5106878663573298e-06
                    ],
                    "UUID": 2083988229
                }
            },
            "Name": "City_building_007",
            "Parent UUID": 346731287,
            "UUID": 1948746188
        },
        "GameObject 7": {
            "Components": {
                "Material": {
                    "Active": true,
                    "Parent UUID": 983154070,
                    "Resource UUID": 268742112,
                    "UUID": 1566361239
                },
                "Mesh": {
                    "Active": true,
                    "F_Normals on": false,
                    "Parent UUID": 983154070,
                    "Resource UUID": 906613416,
                    "UUID": 1217046888,
                    "V_Normals on": false
                },
                "Transform": {
                    "Active": true,
                    "Parent UUID": 983154070,
                    "Rotation": [
                        0.0,
                        0.0,
                        0.7071067690849304,
                        0.7071067690849304
                    ],
                    "Scale": [
                        1.0,
                        1.0,
                        1.0
                    ],
                    "Translation": [
                        40.97999572753906,
                        18.270824432373047,
                        -2.0522466002148576e-06
                    ],
                    "UUID": 1423226639
                }
            },
            "Name": "City_building_008",
            "Parent UUID": 346731287,
            "UUID": 983154070
        },
        "GameObject 8": {
            "Components": {
                "Material": {
                    "Active": true,
                    "Parent UUID": 493282712,
                    "Resource UUID": 2057868010,
                    "UUID": 155089099
                },
                "Mesh": {
                    "Active": true,
                    "F_Normals on": false,
                    "Parent UUID": 493282712,
                    "Resource UUID": 1315563131,
                    "UUID": 1457214605,
                    "V_Normals on": false
                },
                "Transform": {
                    "Active": true,
                    "Parent UUID": 493282712,
                    "Rotation": [
                        0.0,
                        0.0,
                        -0.7071067690849304,
                        0.7071067690849304
                    ],
                    "Scale": [
                        1.0,
                        1.0,
                        1.0
                    ],
                    "Translation": [
                        -2.1597719192504883,
                        1.8538382053375244,
                        0.0
                    ],
                    "UUID": 277209328
                }
            },
            "Name": "Line002",
            "Parent UUID": 346731287,
            "UUID": 493282712
        },
        "GameObject 9": {
            "Components": {
                "Material": {
                    "Active": true,
                    "Parent UUID": 643198801,
                    "Resource UUID": 1656637192,
                    "UUID": 2086495353
                },
                "Mesh": {
                    "Active": true,
                    "F_Normals on": false,
                    "Parent UUID": 643198801,
                    "Resource UUID": 1450452807,
                    "UUID": 1833714803,
                    "V_Normals on": false
                },
                "Transform": {
                    "Active": true,
                    "Parent UUID": 643198801,
                    "Rotation": [
                        0.0,
                        0.0,
                        0.0,
                        1.0
                    ],
                    "Scale": [
                        1.0,
                        1.0,
                        1.0
                    ],
                    "Translation": [
                        -0.02860260009765625,
                        0.026032090187072754,
                        0.0
                    ],
                    "UUID": 814717177
                }
            },
            "Name": "Plane001",
            "Parent UUID": 346731287,
            "UUID": 643198801
        }
    },
    "Resources": {
        "Count": 71,
        "Resource 1": {
            "Exported file": "/library/meshes/street environment_v01 11.mesh",
            "File": "/Assets/FBX/street environment_v01.fbx",
            "Name": "City_building_016_Parent",
            "Type": "Mesh",
            "UUID": 17966549
        },
        "Resource 10": {
            "Exported file": "/library/textures/building_025_c.dds",
            "File": "/Assets/Textures/building_025_c.tga",
            "Height": 256,
            "Name": "building_025_c.dds",
            "Texture": 24,
            "Type": "Texture",
            "UUID": 268742112,
            "Width": 256
        },
        "Resource 11": {
            "Exported file": "/library/textures/building_v02_c.dds",
            "File": "/Assets/Textures/building_v02_c.png",
            "Height": 512,
            "Name": "building_v02_c.dds",
            "Texture": 16,
            "Type": "Texture",
            "UUID": 279239629,
            "Width": 512
        },
        "Resource 12": {
            "Exported file": "/library/textures/building03_c.dds",
            "File": "/Assets/Textures/building03_c.tga",
            "Height": 1024,
            "Name": "building03_c.dds",
            "Texture": 44,
            "Type": "Texture",
            "UUID": 416937446,
            "Width": 1024
        },
        "Resource 13": {
            "Exported file": "/library/meshes/street environment_v01 21.mesh",
            "File": "/Assets/FBX/street environment_v01.fbx",
            "Name": "City_building_030",
            "Type": "Mesh",
            "UUID": 421984235
        },
        "Resource 14": {
            "Exported file": "/library/meshes/street environment_v01 13.mesh",
            "File": "/Assets/FBX/street environment_v01.fbx",
            "Name": "City_building_017_Parent",
            "Type": "Mesh",
            "UUID": 433353045
        },
        "Resource 15": {
            "Exported file": "/library/textures/building 06_ c.dds",
            "File": "/Assets/Textures/building 06_ c.tga",
            "Height": 1024,
            "Name": "building 06_ c.dds",
            "Texture": 96,
            "Type": "Texture",
            "UUID": 445813186,
            "Width": 1024
        },
        "Resource 16": {
            "Exported file": "",
            "File": "/Assets/Textures/",
            "Height": 0,
            "Name": "",
            "Texture": 0,
            "Type": "Texture",
            "UUID": 487801424,
            "Width": 0
        },
        "Resource 17": {
            "Exported file": "/library/textures/building 01_c.dds",
            "File": "/Assets/Textures/building 01_c.tga",
            "Height": 1024,
            "Name": "building 01_c.dds",
            "Texture": 52,
            "Type": "Texture",
            "UUID": 488003215,
            "Width": 1024
        },
        "Resource 18": {
            "Exported file": "/library/meshes/street environment_v01 22.mesh",
            "File": "/Assets/FBX/street environment_v01.fbx",
            "Name": "City_building_031",
            "Type": "Mesh",
            "UUID": 524401109
        },
        "Resource 19": {
            "Exported file": "/library/textures/building_016_c.dds",
            "File": "/Assets/Textures/building_016_c.tga",
            "Height": 256,
            "Name": "building_016_c.dds",
            "Texture": 20,
            "Type": "Texture",
            "UUID": 551058388,
            "Width": 256
        },
        "Resource 2": {
            "Exported file": "/library/meshes/street environment_v01 0.mesh",
            "File": "/Assets/FBX/street environment_v01.fbx",
            "Name": "City_building_004",
            "Type": "Mesh",
            "UUID": 70128045
        },
        "Resource 20": {
            "Exported file": "/library/meshes/street environment_v01 20.mesh",
            "File": "/Assets/FBX/street environment_v01.fbx",
            "Name": "Object010",
            "Type": "Mesh",
            "UUID": 564954208
        },
        "Resource 21": {
            "Exported file": "/library/textures/building 06_ c.dds",
            "File": "/Assets/Textures/building 06_ c.tga",
            "Height": 1024,
            "Name": "building 06_ c.dds",
            "Texture": 40,
            "Type": "Texture",
            "UUID": 622495105,
            "Width": 1024
        },
        "Resource 22": {
            "Exported file": "/library/textures/building_v01_c.dds",
            "File": "/Assets/Textures/building_v01_c.png",
            "Height": 512,
            "Name": "building_v01_c.dds",
            "Texture": 124,
            "Type": "Texture",
            "UUID": 750331867,
            "Width": 512
        },
        "Resource 23": {
            "Exported file": "/library/textures/building 06_ c.dds",
            "File": "/Assets/Textures/building 06_ c.tga",
            "Height": 1024,
            "Name": "building 06_ c.dds",
            "Texture": 108,
            "Type": "Texture",
            "UUID": 756251692,
            "Width": 1024
        },
        "Resource 24": {
            "Exported file": "/library/textures/baker_house.dds",
            "File": "/Assets/Textures/baker_house.png",
            "Height": 1024,
            "Name": "baker_house.dds",
            "Texture": 8,
            "Type": "Texture",
            "UUID": 803039042,
            "Width": 1024
        },
        "Resource 25": {
            "Exported file": "/library/textures/baker_house.dds",
            "File": "/Assets/Textures/baker_house.png",
            "Height": 1024,
            "Name": "baker_house.dds",
            "Texture": 4,
            "Type": "Texture",
            "UUID": 812845538,
            "Width": 1024
        },
        "Resource 26": {
            "Exported file": "/library/meshes/street environment_v01 8.mesh",
            "File": "/Assets/FBX/street environment_v01.fbx",
            "Name": "City_building_011",
            "Type": "Mesh",
            "UUID": 824219090
        },
        "Resource 27": {
            "Exported file": "/library/textures/building03_c.dds",
            "File": "/Assets/Textures/building03_c.tga",
            "Height": 1024,
            "Name": "building03_c.dds",
            "Texture": 12,
            "Type": "Texture",
            "UUID": 876633654,
            "Width": 1024
        },
        "Resource 28": {
            "Exported file": "/library/textures/building05 _c.dds",
            "File": "/Assets/Textures/building05 _c.tga",
            "Height": 1024,
            "Name": "building05 _c.dds",
            "Texture": 116,
            "Type": "Texture",
            "UUID": 894181845,
            "Width": 1024
        },
        "Resource 29": {
            "Exported file": "/library/textures/building05 _c.dds",
            "File": "/Assets/Textures/building05 _c.tga",
            "Height": 1024,
            "Name": "building05 _c.dds",
            "Texture": 100,
            "Type": "Texture",
            "UUID": 898730363,
            "Width": 1024
        },
        "Resource 3": {
            "Exported file": "/library/meshes/street environment_v01 23.mesh",
            "File": "/Assets/FBX/street environment_v01.fbx",
            "Name": "City_building_032",
            "Type": "Mesh",
            "UUID": 113915475
        },
        "Resource 30": {
            "Exported file": "/library/meshes/street environment_v01 26.mesh",
            "File": "/Assets/FBX/street environment_v01.fbx",
            "Name": "City_building_035",
            "Type": "Mesh",
            "UUID": 899560581
        },
        "Resource 31": {
            "Exported file": "/library/meshes/street environment_v01 3.mesh",
            "File": "/Assets/FBX/street environment_v01.fbx",
            "Name": "City_building_008",
            "Type": "Mesh",
            "UUID": 906613416
        },
        "Resource 32": {
            "Exported file": "/library/meshes/street environment_v01 25.mesh",
            "File": "/Assets/FBX/street environment_v01.fbx",
            "Name": "City_building_034",
            "Type": "Mesh",
            "UUID": 941075306
        },
        "Resource 33": {
            "Exported file": "/library/textures/building_v02_c.dds",
            "File": "/Assets/Textures/building_v02_c.png",
            "Height": 512,
            "Name": "building_v02_c.dds",
            "Texture": 128,
            "Type": "Texture",
            "UUID": 1023237889,
            "Width": 512
        },
        "Resource 34": {
            "Exported file": "/library/meshes/street environment_v01 24.mesh",
            "File": "/Assets/FBX/street environment_v01.fbx",
            "Name": "City_building_033",
            "Type": "Mesh",
            "UUID": 1042954143
        },
        "Resource 35": {
            "Exported file": "/library/textures/building_v01_c.dds",
            "File": "/Assets/Textures/building_v01_c.png",
            "Height": 512,
            "Name": "building_v01_c.dds",
            "Texture": 88,
            "Type": "Texture",
            "UUID": 1043783714,
            "Width": 512
        },
        "Resource 36": {
            "Exported file": "/library/textures/building_v01_c.dds",
            "File": "/Assets/Textures/building_v01_c.png",
            "Height": 512,
            "Name": "building_v01_c.dds",
            "Texture": 120,
            "Type": "Texture",
            "UUID": 1059026299,
            "Width": 512
        },
        "Resource 37": {
            "Exported file": "/library/meshes/street environment_v01 31.mesh",
            "File": "/Assets/FBX/street environment_v01.fbx",
            "Name": "City_building_040",
            "Type": "Mesh",
            "UUID": 1071028186
        },
        "Resource 38": {
            "Exported file": "/library/meshes/bakerhouse 1.mesh",
            "File": "/Assets/FBX/bakerhouse.fbx",
            "Name": "Baker_house",
            "Type": "Mesh",
            "UUID": 1074279380
        },
        "Resource 39": {
            "Exported file": "/library/meshes/street environment_v01 6.mesh",
            "File": "/Assets/FBX/street environment_v01.fbx",
            "Name": "City_building_010_Parent",
            "Type": "Mesh",
            "UUID": 1202786986
        },
        "Resource 4": {
            "Exported file": "/library/meshes/street environment_v01 15.mesh",
            "File": "/Assets/FBX/street environment_v01.fbx",
            "Name": "City_building_022",
            "Type": "Mesh",
            "UUID": 120494884
        },
        "Resource 40": {
            "Exported file": "/library/meshes/street environment_v01 12.mesh",
            "File": "/Assets/FBX/street environment_v01.fbx",
            "Name": "City_building_016_SubMesh",
            "Type": "Mesh",
            "UUID": 1223125325
        },
        "Resource 41": {
            "Exported file": "/library/meshes/street environment_v01 10.mesh",
            "File": "/Assets/FBX/street environment_v01.fbx",
            "Name": "City_building_014",
            "Type": "Mesh",
            "UUID": 1228705073
        },
        "Resource 42": {
            "Exported file": "/library/textures/building05 _c.dds",
            "File": "/Assets/Textures/building05 _c.tga",
            "Height": 1024,
            "Name": "building05 _c.dds",
            "Texture": 64,
            "Type": "Texture",
            "UUID": 1240013718,
            "Width": 1024
        },
        "Resource 43": {
            "Exported file": "/library/textures/building 01_c.dds",
            "File": "/Assets/Textures/building 01_c.tga",
            "Height": 1024,
            "Name": "building 01_c.dds",
            "Texture": 28,
            "Type": "Texture",
            "UUID": 1271731231,
            "Width": 1024
        },
        "Resource 44": {
            "Exported file": "/library/meshes/street environment_v01 28.mesh",
            "File": "/Assets/FBX/street environment_v01.fbx",
            "Name": "City_building_037",
            "Type": "Mesh",
            "UUID": 1291104306
        },
        "Resource 45": {
            "Exported file": "/library/textures/building 01_c.dds",
            "File": "/Assets/Textures/building 01_c.tga",
            "Height": 1024,
            "Name": "building 01_c.dds",
            "Texture": 60,
            "Type": "Texture",
            "UUID": 1296701555,
            "Width": 1024
        },
        "Resource 46": {
            "Exported file": "/library/textures/building05 _c.dds",
            "File": "/Assets/Textures/building05 _c.tga",
            "Height": 1024,
            "Name": "building05 _c.dds",
            "Texture": 76,
            "Type": "Texture",
            "UUID": 1308105039,
            "Width": 1024
        },
        "Resource 47": {
            "Exported file": "/library/textures/building 01_c.dds",
            "File": "/Assets/Textures/building 01_c.tga",
            "Height": 1024,
            "Name": "building 01_c.dds",
            "Texture": 48,
            "Type": "Texture",
            "UUID": 1313099917,
            "Width": 1024
        },
        "Resource 48": {
            "Exported file": "/library/meshes/street environment_v01 4.mesh",
            "File": "/Assets/FBX/street environment_v01.fbx",
            "Name": "Line002",
            "Type": "Mesh",
            "UUID": 1315563131
        },
        "Resource 49": {
            "Exported file": "/library/meshes/street environment_v01 19.mesh",
            "File": "/Assets/FBX/street environment_v01.fbx",
            "Name": "City_building_028",
            "Type": "Mesh",
            "UUID": 1391988400
        },
        "Resource 5": {
            "Exported file": "/library/meshes/street environment_v01 29.mesh",
            "File": "/Assets/FBX/street environment_v01.fbx",
            "Name": "City_building_038",
            "Type": "Mesh",
            "UUID": 125126300
        },
        "Resource 50": {
            "Exported file": "/library/meshes/street environment_v01 17.mesh",
            "File": "/Assets/FBX/street environment_v01.fbx",
            "Name": "City_building_024",
            "Type": "Mesh",
            "UUID": 1399271018
        },
        "Resource 51": {
            "Exported file": "/library/textures/building_v01_c.dds",
            "File": "/Assets/Textures/building_v01_c.png",
            "Height": 512,
            "Name": "building_v01_c.dds",
            "Texture": 80,
            "Type": "Texture",
            "UUID": 1416519557,
            "Width": 512
        },
        "Resource 52": {
            "Exported file": "/library/meshes/street environment_v01 2.mesh",
            "File": "/Assets/FBX/street environment_v01.fbx",
            "Name": "City_building_007",
            "Type": "Mesh",
            "UUID": 1442434911
        },
        "Resource 53": {
            "Exported file": "/library/meshes/street environment_v01 5.mesh",
            "File": "/Assets/FBX/street environment_v01.fbx",
            "Name": "Plane001",
            "Type": "Mesh",
            "UUID": 1450452807
        },
        "Resource 54": {
            "Exported file": "/library/textures/building_025_c.dds",
            "File": "/Assets/Textures/building_025_c.tga",
            "Height": 256,
            "Name": "building_025_c.dds",
            "Texture": 72,
            "Type": "Texture",
            "UUID": 1460042857,
            "Width": 256
        },
        "Resource 55": {
            "Exported file": "/library/meshes/street environment_v01 1.mesh",
            "File": "/Assets/FBX/street environment_v01.fbx",
            "Name": "City_building_001",
            "Type": "Mesh",
            "UUID": 1587884574
        },
        "Resource 56": {
            "Exported file": "",
            "File": "/Assets/Textures/",
            "Height": 0,
            "Name": "",
            "Texture": 0,
            "Type": "Texture",
            "UUID": 1656637192,
            "Width": 0
        },
        "Resource 57": {
            "Exported file": "/library/textures/building_v01_c.dds",
            "File": "/Assets/Textures/building_v01_c.png",
            "Height": 512,
            "Name": "building_v01_c.dds",
            "Texture": 84,
            "Type": "Texture",
            "UUID": 1685448609,
            "Width": 512
        },
        "Resource 58": {
            "Exported file": "/library/meshes/street environment_v01 30.mesh",
            "File": "/Assets/FBX/street environment_v01.fbx",
            "Name": "City_building_039",
            "Type": "Mesh",
            "UUID": 1698490272
        },
        "Resource 59": {
            "Exported file": "/library/textures/building_016_c.dds",
            "File": "/Assets/Textures/building_016_c.tga",
            "Height": 256,
            "Name": "building_016_c.dds",
            "Texture": 36,
            "Type": "Texture",
            "UUID": 1703764197,
            "Width": 256
        },
        "Resource 6": {
            "Exported file": "/library/textures/building_v01_c.dds",
            "File": "/Assets/Textures/building_v01_c.png",
            "Height": 512,
            "Name": "building_v01_c.dds",
            "Texture": 104,
            "Type": "Texture",
            "UUID": 210817278,
            "Width": 512
        },
        "Resource 60": {
            "Exported file": "/library/textures/building 01_c.dds",
            "File": "/Assets/Textures/building 01_c.tga",
            "Height": 1024,
            "Name": "building 01_c.dds",
            "Texture": 56,
            "Type": "Texture",
            "UUID": 1713654569,
            "Width": 1024
        },
        "Resource 61": {
            "Exported file": "/library/meshes/street environment_v01 27.mesh",
            "File": "/Assets/FBX/street environment_v01.fbx",
            "Name": "City_building_036",
            "Type": "Mesh",
            "UUID": 1768879107
        },
        "Resource 62": {
            "Exported file": "/library/meshes/street environment_v01 18.mesh",
            "File": "/Assets/FBX/street environment_v01.fbx",
            "Name": "City_building_026",
            "Type": "Mesh",
            "UUID": 1772700343
        },
        "Resource 63": {
            "Exported file": "/library/meshes/bakerhouse 0.mesh",
            "File": "/Assets/FBX/bakerhouse.fbx",
            "Name": "Chimney",
            "Type": "Mesh",
            "UUID": 1857539918
        },
        "Resource 64": {
            "Exported file": "/library/textures/building 01_c.dds",
            "File": "/Assets/Textures/building 01_c.tga",
            "Height": 1024,
            "Name": "building 01_c.dds",
            "Texture": 32,
            "Type": "Texture",
            "UUID": 1858233146,
            "Width": 1024
        },
        "Resource 65": {
            "Exported file": "/library/textures/building03_c.dds",
            "File": "/Assets/Textures/building03_c.tga",
            "Height": 1024,
            "Name": "building03_c.dds",
            "Texture": 92,
            "Type": "Texture",
            "UUID": 1899400488,
            "Width": 1024
        },
        "Resource 66": {
            "Exported file": "/library/meshes/street environment_v01 32.mesh",
            "File": "/Assets/FBX/street environment_v01.fbx",
            "Name": "City_building_041",
            "Type": "Mesh",
            "UUID": 1907586286
        },
        "Resource 67": {
            "Exported file": "/library/meshes/street environment_v01 16.mesh",
            "File": "/Assets/FBX/street environment_v01.fbx",
            "Name": "City_building_023",
            "Type": "Mesh",
            "UUID": 1911855355
        },
        "Resource 68": {
            "Exported file": "/library/textures/building_016_c.dds",
            "File": "/Assets/Textures/building_016_c.tga",
            "Height": 256,
            "Name": "building_016_c.dds",
            "Texture": 68,
            "Type": "Texture",
            "UUID": 1954019543,
            "Width": 256
        },
        "Resource 69": {
            "Exported file": "Model",
            "File": "/assets/fbx/bakerhouse.fbx",
            "Name": "bakerhouse",
            "Type": "Model",
            "UUID": 1991740911
        },
        "Resource 7": {
            "Exported file": "/library/meshes/street environment_v01 9.mesh",
            "File": "/Assets/FBX/street environment_v01.fbx",
            "Name": "City_building_013",
            "Type": "Mesh",
            "UUID": 228644082
        },
        "Resource 70": {
            "Exported file": "",
            "File": "/Assets/Textures/",
            "Height": 0,
            "Name": "",
            "Texture": 0,
            "Type": "Texture",
            "UUID": 2057868010,
            "Width": 0
        },
        "Resource 71": {
            "Exported file": "/library/meshes/street environment_v01 7.mesh",
            "File": "/Assets/FBX/street environment_v01.fbx",
            "Name": "City_building_010_SubMesh",
            "Type": "Mesh",
            "UUID": 2121519325
        },
        "Resource 8": {
            "Exported file": "/library/meshes/street environment_v01 14.mesh",
            "File": "/Assets/FBX/street environment_v01.fbx",
            "Name": "City_building_017_SubMesh",
            "Type": "Mesh",
            "UUID": 234396817
        },
        "Resource 9": {
            "Exported file": "/library/textures/building05 _c.dds",
            "File": "/Assets/Textures/building05 _c.tga",
            "Height": 1024,
            "Name": "building05 _c.dds",
            "Texture": 112,
            "Type": "Texture",
            "UUID": 236705223,
            "Width": 1024
        }
    }
}
